edc_reference/__init__.py
edc_reference/admin.py
edc_reference/admin_site.py
edc_reference/apps.py
edc_reference/model_mixins.py
edc_reference/navbars.py
edc_reference/offline_models.py
edc_reference/populater.py
edc_reference/reference_model_config.py
edc_reference/site_reference.py
edc_reference/system_checks.py
edc_reference/urls.py
edc_reference/views.py
edc_reference/management/__init__.py
edc_reference/management/commands/__init__.py
edc_reference/management/commands/populate_references.py
edc_reference/management/commands/validate_references.py
edc_reference/migrations/0001_initial.py
edc_reference/migrations/0002_reference_value_uuid.py
edc_reference/migrations/0003_reference_related_name.py
edc_reference/migrations/0004_auto_20180116_1528.py
edc_reference/migrations/0005_auto_20190305_0123.py
edc_reference/migrations/0006_auto_20190706_0137.py
edc_reference/migrations/0007_auto_20190706_0706.py
edc_reference/migrations/0008_auto_20190708_0605.py
edc_reference/migrations/0009_auto_20190714_2303.py
edc_reference/migrations/0010_auto_20191024_1000.py
edc_reference/migrations/0011_auto_20200929_0238.py
edc_reference/migrations/0012_alter_reference_managers_reference_site.py
edc_reference/migrations/0013_alter_reference_device_created_and_more.py
edc_reference/migrations/__init__.py
edc_reference/models/__init__.py
edc_reference/models/managers.py
edc_reference/models/reference.py
edc_reference/models/signals.py
edc_reference/reference/__init__.py
edc_reference/reference/reference_deleter.py
edc_reference/reference/reference_getter.py
edc_reference/reference/reference_updater.py
edc_reference/refsets/__init__.py
edc_reference/refsets/fieldset.py
edc_reference/refsets/longitudinal_refsets.py
edc_reference/refsets/refset.py
edc_reference/templates/edc_reference/bootstrap3/home.html
edc_reference/tests/__init__.py
edc_reference/tests/holidays.csv
edc_reference/tests/reference_model_configs_bad.py
edc_reference/tests/reference_test_helper.py
edc_reference-0.3.28.dist-info/AUTHORS
edc_reference-0.3.28.dist-info/LICENSE
edc_reference-0.3.28.dist-info/METADATA
edc_reference-0.3.28.dist-info/WHEEL
edc_reference-0.3.28.dist-info/top_level.txt
edc_reference-0.3.28.dist-info/RECORD
