Metadata-Version: 2.1
Name: edc-reference
Version: 0.3.28
Summary: Pivoted reference model for clinicedc/edc modules
Home-page: https://github.com/clinicedc/edc-reference
Author: Erik van Widenfelt
Author-email: ew2789@gmail.com
License: GPL license, see LICENSE
Keywords: django,edc,clinicedc,clinical trials
Classifier: Environment :: Web Environment
Classifier: Framework :: Django
Classifier: Framework :: Django :: 4.2
Classifier: Intended Audience :: Developers
Classifier: Intended Audience :: Science/Research
Classifier: Operating System :: OS Independent
Classifier: Programming Language :: Python :: 3.11
Classifier: License :: OSI Approved :: GNU General Public License v3 (GPLv3)
Requires-Python: >=3.11
License-File: LICENSE
License-File: AUTHORS
